Metadata-Version: 2.1
Name: tensor2tensor
Version: 1.15.6
Summary: Tensor2Tensor
Home-page: http://github.com/tensorflow/tensor2tensor
Author: Google Inc.
Author-email: no-reply@google.com
License: Apache 2.0
Keywords: tensorflow machine learning
Platform: UNKNOWN
Classifier: Development Status :: 4 - Beta
Classifier: Intended Audience :: Developers
Classifier: Intended Audience :: Science/Research
Classifier: License :: OSI Approved :: Apache Software License
Classifier: Topic :: Scientific/Engineering :: Artificial Intelligence
Provides-Extra: allen
Provides-Extra: tests
Provides-Extra: tensorflow-hub
Provides-Extra: tensorflow
